{
  "$schema": "https://vyges.com/schema/v1/vyges-metadata.schema.json",
  "x-version": "1.0.0",
  "name": "opentitan-tlul",
  "version": "0.1.0",
  "description": "A TileLink Ultra-Lite (TL-UL) adapter for SRAM-like devices, supporting byte-level writes with optional integrity and readback checks.",
  "license": "Apache-2.0",
  "maturity": "production",
  "target": [
    "asic",
    "fpga"
  ],
  "design_type": [
    "digital"
  ],
  "created": "2026-04-23T17:43:14Z",
  "updated": "2026-04-23T17:43:14Z",
  "source": {
    "type": "git",
    "url": "https://github.com/lowRISC/opentitan",
    "commit": "5b8f6746131e231116e685585432b70359d2c727",
    "ip_path": "hw/ip/tlul",
    "private": false,
    "containsEncryptedPayload": false,
    "indexing": true
  },
  "maintainers": [
    {
      "name": "Vyges",
      "email": "team@vyges.com",
      "url": "https://vyges.com",
      "github": "vyges"
    }
  ],
  "interfaces": [
    {
      "type": "clock",
      "direction": "input",
      "protocol": "standard",
      "port": "clk_i",
      "width": 1,
      "description": "Clock input signal"
    },
    {
      "type": "reset",
      "direction": "input",
      "protocol": "active-low",
      "port": "rst_ni",
      "width": 1,
      "description": "Active-low reset signal"
    },
    {
      "type": "bus",
      "direction": "slave",
      "protocol": "TL-UL",
      "port": "tl_i",
      "width": 57,
      "description": "TileLink UL host-to-device interface"
    },
    {
      "type": "bus",
      "direction": "master",
      "protocol": "TL-UL",
      "port": "tl_o",
      "width": 57,
      "description": "TileLink UL device-to-host interface"
    },
    {
      "type": "bus",
      "direction": "master",
      "protocol": "TL-UL",
      "port": "tl_sram_o",
      "width": 57,
      "description": "TileLink UL interface to SRAM"
    },
    {
      "type": "bus",
      "direction": "slave",
      "protocol": "TL-UL",
      "port": "tl_sram_i",
      "width": 57,
      "description": "TileLink UL interface from SRAM"
    },
    {
      "type": "signal",
      "direction": "input",
      "protocol": "custom",
      "port": "error_i",
      "width": 1,
      "description": "Indicates an incoming transaction error"
    },
    {
      "type": "signal",
      "direction": "output",
      "protocol": "custom",
      "port": "error_o",
      "width": 1,
      "description": "Indicates an outgoing transaction error"
    },
    {
      "type": "signal",
      "direction": "output",
      "protocol": "custom",
      "port": "alert_o",
      "width": 1,
      "description": "Alert signal for integrity or other errors"
    },
    {
      "type": "signal",
      "direction": "output",
      "protocol": "custom",
      "port": "compound_txn_in_progress_o",
      "width": 1,
      "description": "Indicates a compound transaction is in progress"
    },
    {
      "type": "signal",
      "direction": "input",
      "protocol": "custom",
      "port": "readback_en_i",
      "width": 4,
      "description": "Enable signal for readback checks"
    },
    {
      "type": "signal",
      "direction": "input",
      "protocol": "custom",
      "port": "wr_collision_i",
      "width": 1,
      "description": "Indicates a write collision"
    },
    {
      "type": "signal",
      "direction": "input",
      "protocol": "custom",
      "port": "write_pending_i",
      "width": 1,
      "description": "Indicates a write is pending"
    }
  ],
  "parameters": [
    {
      "name": "EnableIntg",
      "type": "bit",
      "default": 0,
      "description": "Enable integrity handling at byte level"
    },
    {
      "name": "Outstanding",
      "type": "int",
      "default": 1,
      "description": "Number of outstanding transactions allowed"
    },
    {
      "name": "EnableReadback",
      "type": "bit",
      "default": 0,
      "description": "Enable readback checks on all transactions (requires EnableIntg to be 1)"
    }
  ],
  "performance": {},
  "architecture": {
    "type": "bus",
    "features": [
      "TileLink UL protocol support",
      "Byte-level write integrity handling",
      "Optional readback checks for data integrity",
      "Error handling and alert generation"
    ]
  },
  "asic": {
    "flavor": "digital",
    "technology": [
      "sky130A"
    ]
  },
  "fpga": {
    "toolchain": [
      "Vivado"
    ],
    "devices": [
      "Artix-7"
    ]
  },
  "dependencies": [
    {
      "name": "prim_assert",
      "type": "library",
      "description": "Assertion library for design verification"
    },
    {
      "name": "prim_util_pkg",
      "type": "library",
      "description": "Utility package for parameter calculations"
    },
    {
      "name": "prim_mubi_pkg",
      "type": "library",
      "description": "Multi-bit utility package for integrity checks"
    },
    {
      "name": "top_pkg",
      "type": "library",
      "description": "Top-level package for system-wide constants"
    }
  ],
  "test": {
    "testbenches": [],
    "status": "upstream_passing",
    "coverage": "functional"
  },
  "documentation": {
    "upstream": "https://github.com/lowRISC/opentitan"
  },
  "artifacts": {
    "total_rtl_lines": 5528
  },
  "categories": [
    {
      "main_category": "Interface Controllers",
      "sub_category": "Parallel Interfaces"
    }
  ],
  "keywords": [
    "TileLink",
    "SRAM",
    "adapter",
    "integrity",
    "readback"
  ],
  "trust": {
    "verification_level": "silicon_proven",
    "tapeout_count": 0,
    "fpga_validated": false,
    "formal_verified": false,
    "maintained": true,
    "last_activity": "2026-04-23"
  },
  "meta": {
    "template": {
      "generator": "github-models-ai",
      "template_version": "1.0.0",
      "generated_at": "2026-04-23T17:43:14Z"
    },
    "schema": {
      "version": "1.0.0"
    }
  }
}
